godork-2.6.0.dist-info/licenses/LICENSE
src/__init__.py
src/godork.py
src/helpers/__init__.py
src/helpers/console.py
src/helpers/extractor.py
src/helpers/options.py
src/helpers/reports.py
src/services/__init__.py
src/services/driver.py
src/services/recaptcha.py
src/services/requester.py
src/services/scrape.py
src/services/version.py
src/utils/__init__.py
src/utils/banner.py
src/utils/colors.py
src/utils/exceptions.py
src/utils/parse.py
src/utils/user_agents.py
godork-2.6.0.dist-info/METADATA
godork-2.6.0.dist-info/WHEEL
godork-2.6.0.dist-info/entry_points.txt
godork-2.6.0.dist-info/top_level.txt
godork-2.6.0.dist-info/RECORD
