Metadata-Version: 2.4
Name: godork
Version: 2.6.0
Summary: Advanced & Fast Google Dorking Tool
Home-page: https://github.com/thd3r/godork
Author: Thunder (@thd3r)
Author-email: thd3r@proton.me
License: MIT
Keywords: godork,google dorks,google dorking
Classifier: Development Status :: 4 - Beta
Classifier: Natural Language :: English
Classifier: Programming Language :: Python :: 3
License-File: LICENSE
Requires-Dist: bs4
Requires-Dist: rich
Requires-Dist: pydub
Requires-Dist: psutil
Requires-Dist: aiohttp
Requires-Dist: asyncio
Requires-Dist: selenium
Requires-Dist: setuptools
Requires-Dist: SpeechRecognition
Requires-Dist: webdriver-manager
Requires-Dist: undetected-chromedriver
Dynamic: author
Dynamic: author-email
Dynamic: classifier
Dynamic: description
Dynamic: description-content-type
Dynamic: home-page
Dynamic: keywords
Dynamic: license
Dynamic: license-file
Dynamic: requires-dist
Dynamic: summary
